odoo/addons/maintenance_partner/README.rst
odoo/addons/maintenance_partner/__init__.py
odoo/addons/maintenance_partner/__manifest__.py
odoo/addons/maintenance_partner/i18n/it.po
odoo/addons/maintenance_partner/i18n/maintenance_partner.pot
odoo/addons/maintenance_partner/models/__init__.py
odoo/addons/maintenance_partner/models/maintenance_equipment.py
odoo/addons/maintenance_partner/models/maintenance_request.py
odoo/addons/maintenance_partner/models/res_partner.py
odoo/addons/maintenance_partner/readme/CONTRIBUTORS.md
odoo/addons/maintenance_partner/readme/DESCRIPTION.md
odoo/addons/maintenance_partner/static/description/icon.png
odoo/addons/maintenance_partner/static/description/index.html
odoo/addons/maintenance_partner/tests/__init__.py
odoo/addons/maintenance_partner/tests/test_maintenance_partner.py
odoo/addons/maintenance_partner/views/maintenance_equipment.xml
odoo/addons/maintenance_partner/views/maintenance_request.xml
odoo/addons/maintenance_partner/views/res_partner.xml
odoo_addon_maintenance_partner-18.0.1.0.0.4.dist-info/METADATA
odoo_addon_maintenance_partner-18.0.1.0.0.4.dist-info/WHEEL
odoo_addon_maintenance_partner-18.0.1.0.0.4.dist-info/top_level.txt
odoo_addon_maintenance_partner-18.0.1.0.0.4.dist-info/RECORD
