Metadata-Version: 2.1
Name: odoo-addon-maintenance_partner
Version: 18.0.1.0.0.4
Requires-Python: >=3.10
Requires-Dist: odoo==18.0.*
Summary: Add Partner information in Maintenance Requests and equipments
Home-page: https://github.com/OCA/maintenance
License: AGPL-3
Author: Dixmit,Odoo Community Association (OCA)
Author-email: support@odoo-community.org
Classifier: Programming Language :: Python
Classifier: Framework :: Odoo
Classifier: Framework :: Odoo :: 18.0
Classifier: License :: OSI Approved :: GNU Affero General Public License v3
